exasol/pytest_saas/__init__.py
exasol/pytest_saas/project_short_tag.py
exasol/pytest_saas/version.py
pytest_exasol_saas-0.2.3.dist-info/METADATA
pytest_exasol_saas-0.2.3.dist-info/WHEEL
pytest_exasol_saas-0.2.3.dist-info/entry_points.txt
pytest_exasol_saas-0.2.3.dist-info/RECORD
