Metadata-Version: 2.1
Name: pytest-exasol-saas
Version: 0.2.3
Summary: 
Author: Christoph Kuhnke
Author-email: christoph.kuhnke@exasol.com
Requires-Python: >=3.8,<4
Classifier: Programming Language :: Python :: 3
Classifier: Programming Language :: Python :: 3.8
Classifier: Programming Language :: Python :: 3.9
Classifier: Programming Language :: Python :: 3.10
Classifier: Programming Language :: Python :: 3.11
Classifier: Programming Language :: Python :: 3.12
Requires-Dist: exasol-saas-api (>=0.6.0,<1.0.0)
Requires-Dist: pytest (>=7,<9)
Requires-Dist: pyyaml (>=6.0.1,<7.0.0)
